{"trial_id": "12", "hyperparameters": {"space": [{"class_name": "Choice", "config": {"name": "filters", "default": 32, "conditions": [], "values": [32, 64, 128, 256, 512], "ordered": true}}, {"class_name": "Choice", "config": {"name": "units", "default": 32, "conditions": [], "values": [32, 64, 128, 256, 512], "ordered": true}}, {"class_name": "Choice", "config": {"name": "rate", "default": 0.1, "conditions": [], "values": [0.1, 0.2, 0.3, 0.4, 0.5, 0.6], "ordered": true}}, {"class_name": "Choice", "config": {"name": "output_dim", "default": 64, "conditions": [], "values": [64, 100, 150], "ordered": true}}, {"class_name": "Choice", "config": {"name": "learning_rate", "default": 0.1, "conditions": [], "values": [0.1, 0.01, 0.001, 0.0001], "ordered": true}}], "values": {"filters": 32, "units": 32, "rate": 0.6, "output_dim": 150, "learning_rate": 0.01}}, "metrics": {"metrics": {"loss": {"direction": "min", "observations": [{"value": [0.4603234529495239], "step": 5}]}, "accuracy": {"direction": "max", "observations": [{"value": [0.8339061737060547], "step": 5}]}, "val_loss": {"direction": "min", "observations": [{"value": [0.444797158241272], "step": 5}]}, "val_accuracy": {"direction": "max", "observations": [{"value": [0.844567596912384], "step": 5}]}}}, "score": 0.8339061737060547, "best_step": 5, "status": "COMPLETED", "message": null}